{"mainPropery":{"diseaseId":13215,"diseaseName":"Renal cell carcinoma","hasGardWebPage":true,"isRare":true,"websiteUrl":"https://rarediseases.info.nih.gov/diseases/13215/renal-cell-carcinoma","synonyms":["Adenocarcinoma of Kidney","Renal Cell Adenocarcinoma"],"synonyms-with-source":[{"name":"Adenocarcinoma of Kidney","source":"NCI Thesaurus"},{"name":"Renal Cell Adenocarcinoma","source":"NCI Thesaurus"}],"identifiers":[{"identifierType":"NCI Thesaurus","identifierId":"C9385"}]},"diseaseCategories":[],"organizations":[],"resource descriptions":[],"overviewQuestion":{"questionId":0,"dateModified":"0001-01-01T00:00:00"},"basicQuestions":[],"references":[],"relatedDiseases":[{"relatedDiseaseId":9339,"relatedDiseaseName":"Kidney Neoplasm","relation":"Parent","isRare":false,"hasGardPage":true}],"gardCases":[],"news":[{"newsId":671,"dateCreated":"2020-05-20T13:39:00","publishDate":"2020-05-22T00:00:00","title":"NIH-Supported Research Survey to Examine Impact of COVID-19 on Rare Diseases Community","description":"The NIH-funded Rare Diseases Clinical Research Network (RDCRN) has launched an <a href=\"https://www.rarediseasesnetwork.org/COVIDsurvey \" target=\"_blank\">online research survey</a> to find out how the COVID-19 pandemic is impacting individuals with rare diseases, their families and their caregivers. Your participation can help the rare disease research community shed light on the needs of people with rare diseases during this and other potential health crises, in addition to informing future research efforts. The survey must be completed by December 15, 2020.","url":"https://www.rarediseasesnetwork.org/COVIDsurvey","lastModified":"2020-11-30T14:44:00","isFeatured":false}],"conferences":[],"phenoTypes":[],"medicalProducts":[],"EncodedName":"Renal_cell_carcinoma"}